certomancer/__init__.py
certomancer/__main__.py
certomancer/_asn1_types.py
certomancer/cli.py
certomancer/config_utils.py
certomancer/crypto_utils.py
certomancer/default_plugins.py
certomancer/py.typed
certomancer/services.py
certomancer/version.py
certomancer/integrations/__init__.py
certomancer/integrations/alchemist.py
certomancer/integrations/animator.py
certomancer/integrations/illusionist.py
certomancer/integrations/animator_templates/arch_summary.html
certomancer/integrations/animator_templates/index.html
certomancer/registry/__init__.py
certomancer/registry/common.py
certomancer/registry/config.py
certomancer/registry/entities.py
certomancer/registry/keys.py
certomancer/registry/pki_arch.py
certomancer/registry/plugin_api.py
certomancer/registry/issued/__init__.py
certomancer/registry/issued/attr_cert.py
certomancer/registry/issued/cert.py
certomancer/registry/issued/general.py
certomancer/registry/svc_config/__init__.py
certomancer/registry/svc_config/api.py
certomancer/registry/svc_config/cert_repo.py
certomancer/registry/svc_config/crl.py
certomancer/registry/svc_config/ocsp.py
certomancer/registry/svc_config/tsa.py
certomancer-0.13.0.dist-info/licenses/LICENSE
certomancer-0.13.0.dist-info/METADATA
certomancer-0.13.0.dist-info/WHEEL
certomancer-0.13.0.dist-info/entry_points.txt
certomancer-0.13.0.dist-info/top_level.txt
certomancer-0.13.0.dist-info/RECORD
