Metadata-Version: 2.4
Name: certomancer
Version: 0.13.0
Summary: PKI testing tool
Author-email: Matthias Valvekens <dev@mvalvekens.be>
License: MIT
Project-URL: Homepage, https://github.com/MatthiasValvekens/certomancer
Keywords: pki,testing
Classifier: Development Status :: 4 - Beta
Classifier: Intended Audience :: Developers
Classifier: License :: OSI Approved :: MIT License
Classifier: Programming Language :: Python :: 3.9
Classifier: Programming Language :: Python :: 3.10
Classifier: Programming Language :: Python :: 3.11
Classifier: Programming Language :: Python :: 3.12
Classifier: Programming Language :: Python :: 3.13
Classifier: Topic :: Security :: Cryptography
Classifier: Topic :: Software Development :: Libraries :: Python Modules
License-File: LICENSE
Requires-Dist: asn1crypto==1.5.*
Requires-Dist: click>=7.1.2
Requires-Dist: pyyaml>=5.4.1
Requires-Dist: python-dateutil>=2.8.1
Requires-Dist: tzlocal>=2.1
Requires-Dist: cryptography>=3.4.7
Provides-Extra: requests-mocker
Requires-Dist: requests-mock>=1.8.0; extra == "requests-mocker"
Provides-Extra: web-api
Requires-Dist: Werkzeug>=2.2.3; extra == "web-api"
Requires-Dist: Jinja2>=2.11.3; extra == "web-api"
Provides-Extra: pkcs11
Requires-Dist: python-pkcs11~=0.7.0; extra == "pkcs11"
Provides-Extra: testing-minimal
Requires-Dist: pytest>=6.1.1; extra == "testing-minimal"
Requires-Dist: pytz>=2020.1; extra == "testing-minimal"
Requires-Dist: freezegun>=1.1.0; extra == "testing-minimal"
Requires-Dist: requests>=2.0.0; extra == "testing-minimal"
Requires-Dist: pytest-cov~=4.0.0; extra == "testing-minimal"
Requires-Dist: pytest-asyncio==0.21.0; extra == "testing-minimal"
Requires-Dist: certomancer[requests-mocker,web-api]; extra == "testing-minimal"
Provides-Extra: testing
Requires-Dist: pyhanko-certvalidator==0.26.5; extra == "testing"
Requires-Dist: certomancer[pkcs11,testing-minimal]; extra == "testing"
Provides-Extra: mypy
Requires-Dist: types-requests; extra == "mypy"
Requires-Dist: types-python-dateutil; extra == "mypy"
Requires-Dist: types-PyYAML; extra == "mypy"
Requires-Dist: types-tzlocal; extra == "mypy"
Requires-Dist: certomancer[testing]; extra == "mypy"
Dynamic: license-file
